conduit/__init__.py
conduit/conf/configen.yaml
conduit/data/__init__.py
conduit/data/constants.py
conduit/data/datamodules/__init__.py
conduit/data/datamodules/audio/__init__.py
conduit/data/datamodules/audio/base.py
conduit/data/datamodules/audio/ecoacoustics.py
conduit/data/datamodules/base.py
conduit/data/datamodules/tabular/__init__.py
conduit/data/datamodules/tabular/base.py
conduit/data/datamodules/tabular/dummy.py
conduit/data/datamodules/vision/__init__.py
conduit/data/datamodules/vision/base.py
conduit/data/datamodules/vision/camelyon17.py
conduit/data/datamodules/vision/celeba.py
conduit/data/datamodules/vision/cmnist.py
conduit/data/datamodules/vision/dummy.py
conduit/data/datamodules/vision/nico.py
conduit/data/datamodules/vision/nico_plus_plus.py
conduit/data/datamodules/vision/pacs.py
conduit/data/datamodules/vision/waterbirds.py
conduit/data/datasets/__init__.py
conduit/data/datasets/audio/__init__.py
conduit/data/datasets/audio/base.py
conduit/data/datasets/audio/ecoacoustics.py
conduit/data/datasets/base.py
conduit/data/datasets/tabular/__init__.py
conduit/data/datasets/tabular/base.py
conduit/data/datasets/tabular/dummy.py
conduit/data/datasets/utils.py
conduit/data/datasets/vision/__init__.py
conduit/data/datasets/vision/base.py
conduit/data/datasets/vision/camelyon17.py
conduit/data/datasets/vision/celeba.py
conduit/data/datasets/vision/cmnist.py
conduit/data/datasets/vision/dummy.py
conduit/data/datasets/vision/fmow.py
conduit/data/datasets/vision/isic.py
conduit/data/datasets/vision/iwildcam.py
conduit/data/datasets/vision/nico.py
conduit/data/datasets/vision/nico_plus_plus.py
conduit/data/datasets/vision/nih.py
conduit/data/datasets/vision/pacs.py
conduit/data/datasets/vision/ssrp.py
conduit/data/datasets/vision/utils.py
conduit/data/datasets/vision/waterbirds/__init__.py
conduit/data/datasets/vision/waterbirds/waterbirds.py
conduit/data/datasets/vision/waterbirds/waterbirds_fixed.csv.zip
conduit/data/datasets/vision/wrappers.py
torch_conduit-0.4.2.dist-info/LICENSE
torch_conduit-0.4.2.dist-info/METADATA
torch_conduit-0.4.2.dist-info/WHEEL
torch_conduit-0.4.2.dist-info/RECORD
